bidlp/__init__.py
bidlp/bidlp.py
bidlp-0.1.0.dist-info/AUTHORS.rst
bidlp-0.1.0.dist-info/LICENSE
bidlp-0.1.0.dist-info/METADATA
bidlp-0.1.0.dist-info/WHEEL
bidlp-0.1.0.dist-info/top_level.txt
bidlp-0.1.0.dist-info/RECORD
