Metadata-Version: 2.1
Name: bidlp
Version: 0.1.0
Summary: bid language process
Home-page: https://github.com/bidfit/bidlp
Author: bidlp
Author-email: devel0per1991@outlook.com
License: MIT license
Keywords: bidlp
Platform: UNKNOWN
Classifier: Development Status :: 2 - Pre-Alpha
Classifier: Intended Audience :: Developers
Classifier: License :: OSI Approved :: MIT License
Classifier: Natural Language :: English
Classifier: Programming Language :: Python :: 3
Classifier: Programming Language :: Python :: 3.5
Classifier: Programming Language :: Python :: 3.6
Classifier: Programming Language :: Python :: 3.7
Classifier: Programming Language :: Python :: 3.8
Requires-Python: >=3.5
